mudp/__init__.py
mudp/__main__.py
mudp/connection.py
mudp/encryption.py
mudp/node.py
mudp/rx_message_handler.py
mudp/singleton.py
mudp/tx_message_handler.py
mudp-1.0.0a7.dist-info/LICENSE
mudp-1.0.0a7.dist-info/METADATA
mudp-1.0.0a7.dist-info/WHEEL
mudp-1.0.0a7.dist-info/entry_points.txt
mudp-1.0.0a7.dist-info/RECORD
